MANIFEST.in
README.txt
setup.cfg
setup.py
fixture/__init__.py
fixture/base.py
fixture/django_testcase.py
fixture/docs.py
fixture/exc.py
fixture/io.py
fixture/style.py
fixture/util.py
fixture.egg-info/PKG-INFO
fixture.egg-info/SOURCES.txt
fixture.egg-info/dependency_links.txt
fixture.egg-info/entry_points.txt
fixture.egg-info/requires.txt
fixture.egg-info/top_level.txt
fixture/command/__init__.py
fixture/command/generate/__init__.py
fixture/command/generate/generate.py
fixture/command/generate/generate_sqlalchemy.py
fixture/command/generate/generate_sqlobject.py
fixture/command/generate/template.py
fixture/dataset/__init__.py
fixture/dataset/converter.py
fixture/dataset/dataset.py
fixture/examples/__init__.py
fixture/examples/db/__init__.py
fixture/examples/db/sqlalchemy_examples.py
fixture/examples/db/sqlobject_examples.py
fixture/examples/db/storm_examples.py
fixture/loadable/__init__.py
fixture/loadable/django_loadable.py
fixture/loadable/google_datastore_loadable.py
fixture/loadable/loadable.py
fixture/loadable/sqlalchemy_loadable.py
fixture/loadable/sqlobject_loadable.py
fixture/loadable/storm_loadable.py
fixture/setup_cmd/__init__.py
fixture/setup_cmd/apidocs.py
fixture/test/__init__.py
fixture/test/conf.py
fixture/test/env_supports.py
fixture/test/test_base.py
fixture/test/test_io.py
fixture/test/test_command/__init__.py
fixture/test/test_command/test_generate/__init__.py
fixture/test/test_command/test_generate/test_generate.py
fixture/test/test_command/test_generate/test_generate_sqlalchemy.py
fixture/test/test_command/test_generate/test_generate_sqlobject.py
fixture/test/test_loadable/__init__.py
fixture/test/test_loadable/test_google_datastore_loadable.py
fixture/test/test_loadable/test_loadable.py
fixture/test/test_loadable/test_loadable_queue.py
fixture/test/test_loadable/test_sqlalchemy_loadable.py
fixture/test/test_loadable/test_sqlobject_loadable.py
fixture/test/test_loadable/test_storm_loadable.py
fixture/test/test_loadable/test_django/__init__.py
fixture/test/test_loadable/test_django/fixtures.py
fixture/test/test_loadable/test_django/test_djangoenv.py
fixture/test/test_loadable/test_django/test_djangomeduim.py
